pml.py
pml-1.19.dist-info/DESCRIPTION.rst
pml-1.19.dist-info/METADATA
pml-1.19.dist-info/RECORD
pml-1.19.dist-info/WHEEL
pml-1.19.dist-info/metadata.json
pml-1.19.dist-info/top_level.txt
