Metadata-Version: 2.0
Name: pml
Version: 1.19
Summary: simple, elegant HTML, XHTML and XML generation
Home-page: http://pypi.python.org/pypi/pml
Author: Richard Jones
Author-email: rjones@ekit-inc.com
License: UNKNOWN
Platform: UNKNOWN
Classifier: Environment :: Web Environment
Classifier: Intended Audience :: Developers
Classifier: Programming Language :: Python :: 2.5
Classifier: Programming Language :: Python :: 2.6
Classifier: Programming Language :: Python :: 2.7
Classifier: Programming Language :: Python :: 3
Classifier: Topic :: Software Development :: Code Generators
Classifier: Topic :: Software Development :: Libraries :: Python Modules
Classifier: Topic :: Text Processing :: Markup :: HTML
Classifier: License :: OSI Approved :: BSD License
